ICIW_Plots/ICIWlatex.mplstyle
ICIW_Plots/ICIWnobg.mplstyle
ICIW_Plots/ICIWstyle.mplstyle
ICIW_Plots/__init__.py
ICIW_Plots/colors.py
ICIW_Plots/cyclers.py
ICIW_Plots/figures.py
ICIW_Plots/layout.py
ICIW_Plots/plots.py
_junk/Scientific_Plot.py
_junk/colors.py
_junk/setup.py
_junk/subplots.py
iciw_plots-1.0.43.dist-info/licenses/LICENSE.txt
iciw_plots-1.0.43.dist-info/METADATA
iciw_plots-1.0.43.dist-info/WHEEL
iciw_plots-1.0.43.dist-info/top_level.txt
iciw_plots-1.0.43.dist-info/RECORD
