Metadata-Version: 2.4
Name: ICIW_Plots
Version: 1.0.43
Summary: A collection of tools for use in the Institute of Chemical Engineering at Ulm University.
Author-email: Hannes Stagge <hannes.stagge@uni-ulm.de>
License: MIT License
Project-URL: homepage, https://gitlab.uni-ulm.de/ciw-ag-g-ttel/private/misc/iciw_plots
License-File: LICENSE.txt
Requires-Dist: numpy
Requires-Dist: matplotlib
Dynamic: license-file
